ryca_django_grpc/__init__.py
ryca_django_grpc/apps.py
ryca_django_grpc/generics.py
ryca_django_grpc/mixins.py
ryca_django_grpc/permissions.py
ryca_django_grpc/proto_serializers.py
ryca_django_grpc/services.py
ryca_django_grpc/settings.py
ryca_django_grpc/signals.py
ryca_django_grpc/test.py
ryca_django_grpc/management/__init__.py
ryca_django_grpc/management/commands/__init__.py
ryca_django_grpc/management/commands/generateproto.py
ryca_django_grpc/management/commands/grpcrunserver.py
ryca_django_grpc/protobuf/__init__.py
ryca_django_grpc/protobuf/generators.py
ryca_django_grpc/protobuf/json_format.py
ryca_django_grpc/utils/__init__.py
ryca_django_grpc/utils/model_meta.py
ryca_django_grpc-1.0.13.dist-info/LICENSE
ryca_django_grpc-1.0.13.dist-info/METADATA
ryca_django_grpc-1.0.13.dist-info/WHEEL
ryca_django_grpc-1.0.13.dist-info/top_level.txt
ryca_django_grpc-1.0.13.dist-info/RECORD
